backend/__init__.py
backend/main.py
backend/models.py
backend/prompts.py
backend/routes.py
backend/schemas.py
backend/utils.py
backend/memory/__init__.py
backend/memory/llm_utils.py
backend/memory/rag_utils.py
recall_core/__init__.py
recall_core/reca11.py
recall_core-0.1.1.dist-info/licenses/LICENSE
recall_core-0.1.1.dist-info/METADATA
recall_core-0.1.1.dist-info/WHEEL
recall_core-0.1.1.dist-info/top_level.txt
recall_core-0.1.1.dist-info/RECORD
