Metadata-Version: 2.4
Name: recall-core
Version: 0.1.1
Summary: Memory layer and SDK for LLMs
Requires-Python: >=3.9
License-File: LICENSE
Requires-Dist: fastapi>=0.116.1
Requires-Dist: openai>=1.98.0
Requires-Dist: pinecone>=7.3.0
Requires-Dist: python-dotenv>=1.1.1
Requires-Dist: slowapi>=0.1.9
Requires-Dist: uvicorn>=0.35.0
Requires-Dist: requests>=2.0.0
Requires-Dist: pymongo>=4.13.2
Requires-Dist: build>=1.3.0
Requires-Dist: twine>=6.1.0
Dynamic: license-file
